edolab/__init__.py
edolab/__main__.py
edolab/run.py
edolab/summarise.py
edolab/version.py
edolab-0.0.6.dist-info/LICENSE
edolab-0.0.6.dist-info/METADATA
edolab-0.0.6.dist-info/WHEEL
edolab-0.0.6.dist-info/entry_points.txt
edolab-0.0.6.dist-info/top_level.txt
edolab-0.0.6.dist-info/RECORD
