Metadata-Version: 2.1
Name: edolab
Version: 0.0.6
Summary: A command line tool for running experiments with `edo`.
Home-page: https://github.com/daffidwilde/edolab
Author: Henry Wilde
Author-email: henrydavidwilde@gmail.com
License: MIT
Keywords: artificial data,evolutionary algorithm,experiments
Platform: UNKNOWN
Requires-Python: >=3.6
Requires-Dist: click
Requires-Dist: cloudpickle
Requires-Dist: edo (>=0.3)
Requires-Dist: tqdm
